acp/__init__.py
acp/methods.py
acp_package-0.0.8.dist-info/LICENSE
acp_package-0.0.8.dist-info/METADATA
acp_package-0.0.8.dist-info/WHEEL
acp_package-0.0.8.dist-info/top_level.txt
acp_package-0.0.8.dist-info/RECORD
