Metadata-Version: 2.1
Name: acp-package
Version: 0.0.8
Summary: python implementation of Approximate full Conformal Prediction (ACP)
Home-page: https://github.com/cambridge-mlg/acp
Author: Javier Abad
Author-email: jaabmar@gmail.com
License: UNKNOWN
Project-URL: Bug Tracker, https://github.com/cambridge-mlg/acp/issues
Platform: UNKNOWN
Classifier: Programming Language :: Python :: 3
Classifier: License :: OSI Approved :: MIT License
Classifier: Operating System :: OS Independent
Requires-Python: >=3.6
License-File: LICENSE
